LICENSE
MANIFEST.in
README.md
requirements.txt
setup.py
Appli/__init__.py
MovieSerieTorrent/__init__.py
MovieSerieTorrent/formatting.py
MovieSerieTorrent/info.py
MovieSerieTorrent/parser.py
MovieSerieTorrent/renamer.py
MovieSerieTorrent.egg-info/PKG-INFO
MovieSerieTorrent.egg-info/SOURCES.txt
MovieSerieTorrent.egg-info/dependency_links.txt
MovieSerieTorrent.egg-info/requires.txt
MovieSerieTorrent.egg-info/top_level.txt
tests/Rename_test.py
tests/__init__.py