Metadata-Version: 1.1
Name: MovieSerieTorrent
Version: 1.0.16
Summary: Parser and Renamer for torrents files (Movies and series)
Home-page: https://github.com/JonathanPetit/Parser-Renamer
Author: Petit Jonathan
Author-email: petit.jonathan16@gmail.com
License: MIT
Keywords: parser renamer formatting python torrents torrent files file movie serie movies series
Platform: UNKNOWN
Classifier: Programming Language :: Python
Classifier: Natural Language :: French
Classifier: Operating System :: OS Independent
Classifier: Programming Language :: Python :: 2.7
Classifier: Programming Language :: Python :: 3
Classifier: Programming Language :: Python :: 3.3
